MANIFEST.in
README.md
setup.py
bpy_lambda/__init__.py
bpy_lambda/libGLU.so.1
bpy_lambda/libpython3.5m.so.1.0
bpy_lambda/2.78/scripts/addons/add_curve_ivygen.py
bpy_lambda/2.78/scripts/addons/animation_add_corrective_shape_key.py
bpy_lambda/2.78/scripts/addons/animation_animall.py
bpy_lambda/2.78/scripts/addons/bone_selection_sets.py
bpy_lambda/2.78/scripts/addons/camera_dolly_crane_rigs.py
bpy_lambda/2.78/scripts/addons/camera_turnaround.py
bpy_lambda/2.78/scripts/addons/curve_simplify.py
bpy_lambda/2.78/scripts/addons/development_api_navigator.py
bpy_lambda/2.78/scripts/addons/development_edit_operator.py
bpy_lambda/2.78/scripts/addons/development_icon_get.py
bpy_lambda/2.78/scripts/addons/development_iskeyfree.py
bpy_lambda/2.78/scripts/addons/development_ui_classes.py
bpy_lambda/2.78/scripts/addons/game_engine_publishing.py
bpy_lambda/2.78/scripts/addons/game_engine_save_as_runtime.py
bpy_lambda/2.78/scripts/addons/io_anim_camera.py
bpy_lambda/2.78/scripts/addons/io_export_after_effects.py
bpy_lambda/2.78/scripts/addons/io_export_paper_model.py
bpy_lambda/2.78/scripts/addons/io_export_pc2.py
bpy_lambda/2.78/scripts/addons/io_export_unreal_psk_psa.py
bpy_lambda/2.78/scripts/addons/io_import_gimp_image_to_scene.py
bpy_lambda/2.78/scripts/addons/io_import_images_as_planes.py
bpy_lambda/2.78/scripts/addons/io_import_scene_lwo.py
bpy_lambda/2.78/scripts/addons/io_import_scene_unreal_psa_psk.py
bpy_lambda/2.78/scripts/addons/lighting_dynamic_sky.py
bpy_lambda/2.78/scripts/addons/mesh_auto_mirror.py
bpy_lambda/2.78/scripts/addons/mesh_bsurfaces.py
bpy_lambda/2.78/scripts/addons/mesh_carver.py
bpy_lambda/2.78/scripts/addons/mesh_custom_normals_tools.py
bpy_lambda/2.78/scripts/addons/mesh_f2.py
bpy_lambda/2.78/scripts/addons/mesh_looptools.py
bpy_lambda/2.78/scripts/addons/mesh_relax.py
bpy_lambda/2.78/scripts/addons/mesh_snap_utilities_line.py
bpy_lambda/2.78/scripts/addons/node_wrangler.py
bpy_lambda/2.78/scripts/addons/object_animrenderbake.py
bpy_nibbler.egg-info/PKG-INFO
bpy_nibbler.egg-info/SOURCES.txt
bpy_nibbler.egg-info/dependency_links.txt
bpy_nibbler.egg-info/top_level.txt