Metadata-Version: 1.0
Name: bpy-nibbler
Version: 0.1
Summary: A compiled binary of Blender-as-a-Python-Module (bpy) for use in AWS Lambda with cycles
Home-page: https://github.com/johndavidmartinez/bpy_lambda
Author: John Martinez
Author-email: johndavidmartinez1@gmail.com
License: UNKNOWN
Platform: UNKNOWN
